aiohttp_ext/__init__.py
aiohttp_ext/auth/__init__.py
aiohttp_ext/auth/auth_backends.py
aiohttp_ext/auth/decorators.py
aiohttp_ext/auth/exceptions.py
aiohttp_ext/auth/extension.py
aiohttp_ext/auth/script_commands.py
aiohttp_ext/auth/test/__init__.py
aiohttp_ext/auth/test/settings.py
aiohttp_ext/auth/test/test_aiohttp_ext_auth.py
aiohttp_ext.auth-0.1.2.dist-info/METADATA
aiohttp_ext.auth-0.1.2.dist-info/WHEEL
aiohttp_ext.auth-0.1.2.dist-info/top_level.txt
aiohttp_ext.auth-0.1.2.dist-info/RECORD
