Metadata-Version: 2.1
Name: aiohttp-ext.auth
Version: 0.1.2
Summary: Пользователи и авторизация
Home-page: https://bitbucket.org/igor_kovalenko/aiohttp_ext.auth
Author: Kovalenko Igor
Author-email: kovalenko.s.igor@gmail.com
License: BSD
Platform: any
Classifier: Environment :: Web Environment
Classifier: Intended Audience :: Developers
Classifier: License :: OSI Approved :: BSD License
Classifier: Operating System :: OS Independent
Classifier: Programming Language :: Python
Classifier: Topic :: Internet :: WWW/HTTP :: Dynamic Content
Classifier: Topic :: Software Development :: Libraries :: Python Modules
Requires-Dist: aiohttp (==3.6.2)
Requires-Dist: aiodns (==2.0.0)
Requires-Dist: sqlalchemy-utils (==0.33.5)
Requires-Dist: passlib (==1.7.1)
Requires-Dist: pyjwt (==1.6.4)
Requires-Dist: cryptography (==2.3.1)
